py_test_package/__init__.py
py_test_package-0.0.4.dist-info/LICENSE
py_test_package-0.0.4.dist-info/METADATA
py_test_package-0.0.4.dist-info/WHEEL
py_test_package-0.0.4.dist-info/top_level.txt
py_test_package-0.0.4.dist-info/RECORD
