Metadata-Version: 2.1
Name: py_test_package
Version: 0.0.4
Summary: Testing python packaging
Author-email: "Michael J. Williams" <michaeljw1@googlemail.com>
License: MIT
Classifier: Programming Language :: Python :: 3
Requires-Python: >=3.8
License-File: LICENSE
